llm_jq.py
llm_jq-0.1.1.dist-info/LICENSE
llm_jq-0.1.1.dist-info/METADATA
llm_jq-0.1.1.dist-info/WHEEL
llm_jq-0.1.1.dist-info/entry_points.txt
llm_jq-0.1.1.dist-info/top_level.txt
llm_jq-0.1.1.dist-info/RECORD
