Metadata-Version: 2.1
Name: llm-jq
Version: 0.1.1
Summary: Write and execute jq programs with the help of LLM
Author: Simon Willison
License: Apache-2.0
Project-URL: Homepage, https://github.com/simonw/llm-jq
Project-URL: Changelog, https://github.com/simonw/llm-jq/releases
Project-URL: Issues, https://github.com/simonw/llm-jq/issues
Project-URL: CI, https://github.com/simonw/llm-jq/actions
Classifier: License :: OSI Approved :: Apache Software License
Requires-Python: >=3.9
License-File: LICENSE
Requires-Dist: llm
Provides-Extra: test
Requires-Dist: pytest ; extra == 'test'
